item_synchronizer/__init__.py
item_synchronizer/helpers.py
item_synchronizer/py.typed
item_synchronizer/resolution_strategy.py
item_synchronizer/synchronizer.py
item_synchronizer/types.py
item_synchronizer-1.1.5.dist-info/LICENSE.md
item_synchronizer-1.1.5.dist-info/METADATA
item_synchronizer-1.1.5.dist-info/WHEEL
item_synchronizer-1.1.5.dist-info/RECORD
