Metadata-Version: 2.1
Name: item_synchronizer
Version: 1.1.5
Summary: Synchronize items bi-directionally between two different sources
Home-page: https://github.com/bergercookie/item_synchronizer
License: MIT
Author: Nikos Koukis
Author-email: nickkouk@gmail.com
Requires-Python: >=3.8,<4.0
Classifier: Framework :: Pytest
Classifier: License :: OSI Approved :: MIT License
Classifier: Natural Language :: English
Classifier: Operating System :: Unix
Classifier: Programming Language :: Python :: 3
Classifier: Programming Language :: Python :: 3.8
Classifier: Programming Language :: Python :: 3.9
Classifier: Programming Language :: Python :: 3.10
Classifier: Programming Language :: Python :: 3.11
Classifier: Programming Language :: Python :: 3.12
Classifier: Topic :: Utilities
Requires-Dist: bidict (>=0.21.4,<0.22.0)
Requires-Dist: bubop (>=0.1.8,<0.2)
Project-URL: Repository, https://github.com/bergercookie/item_synchronizer
